Workbook

Sheet Assumptions
A1: Kotkoa shop — POD Pricing Assumptions
A2: Global % assumptions used by every product in 'Price Calculator' and 'Product List'.
A4: Assumption | B4: Value | C4: Notes
A5: Payment processing fee (%) | B5: 0.029 | C5: Stripe / Shopify Payments standard rate
A6: Payment processing fixed fee ($) | B6: 0.3 | C6: Per-transaction fixed fee (Stripe/Shopify Payments)
A7: Refund / reprint reserve (%) | B7: 0.04 | C7: Buffer for returns, damaged prints, reprints
A8: Advertising reserve (%) | B8: 0.25 | C8: Share of price reserved to cover ad spend (CAC). Lower once CPA stabilizes
A9: Target contribution margin (%) | B9: 0.2 | C9: Desired profit left after all costs above
A10: VAT / IVA rate (%) — if prices are tax-inclusive | B10: 0 | C10: Spain/EU: set >0 only if displayed price must include VAT
A13: Formula used
A14: price = (product cost + shipping + fixed payment fee) / (1 − fee% − refund% − ad% − margin% − VAT%)
A16: Edit only the yellow cells. Everything else recalculates automatically.

Sheet Price Calculator
A1: Single Product Price Calculator
A3: Product name | B3: Bella Canvas T-Shirt
A5: Cost inputs
A6: Printify product cost ($) | B6: 9 | C6: Printify base cost for this product
A7: Printify shipping cost ($) | B7: 5 | C7: From Printify shipping profile for chosen print location
A9: Calculated price
A10: Recommended sale price ($) | B10: =(B6+B7+Assumptions!$B$6)/(1-Assumptions!$B$5-Assumptions!$B$7-Assumptions!$B$8-Assumptions!$B$9-Assumptions!$B$10) -> 29.72973 | C10: Formula: (cost + shipping + fixed fee) / (1 − fee% − refund% − ad% − margin% − VAT%)
A11: Rounded sale price (psychological, .99) | B11: =ROUNDUP(B10,0)-0.01 -> 29.99 | C11: Rounds up to nearest whole dollar, then ends in .99
A13: Breakdown at rounded price
A14: Sale price | B14: =B11 -> 29.99
A15: Printify product cost | B15: =-B6 -> -9
A16: Printify shipping | B16: =-B7 -> -5
A17: Payment processing fee | B17: =-(B11*Assumptions!$B$5+Assumptions!$B$6) -> -1.16971
A18: Refund / reprint reserve | B18: =-B11*Assumptions!$B$7 -> -1.1996
A19: Advertising reserve | B19: =-B11*Assumptions!$B$8 -> -7.4975
A20: VAT / IVA (if applicable) | B20: =-B11*Assumptions!$B$10 -> 0
A21: Contribution margin ($) | B21: =SUM(B14:B20) -> 6.12319
A22: Contribution margin (%) | B22: =B21/B11 -> 0.20417439
A24: Change assumptions (fees, ad reserve, target margin) on the 'Assumptions' tab.

Sheet Product List
A1: Product Pricing — Bulk Calculator
A2: Fill in yellow cells (name, cost, shipping) for each product. Everything else auto-calculates.
A4: Product name | B4: Printify cost ($) | C4: Printify shipping ($) | D4: Calculated price ($) | E4: Rounded price ($) | F4: Contribution margin ($) | G4: Contribution margin (%)
A5: Bella Canvas T-Shirt | B5: 9 | C5: 5 | D5: =(B5+C5+Assumptions!$B$6)/(1-Assumptions!$B$5-Assumptions!$B$7-Assumptions!$B$8-Assumptions!$B$9-Assumptions!$B$10) -> 29.72973 | E5: =ROUNDUP(D5,0)-0.01 -> 29.99 | F5: =E5-B5-C5-(E5*Assumptions!$B$5+Assumptions!$B$6)-E5*Assumptions!$B$7-E5*Assumptions!$B$8-E5*Assumptions!$B$10 -> 6.12319 | G5: =F5/E5 -> 0.20417439
A6: Premium Hoodie | B6: 22 | C6: 6.5 | D6: =(B6+C6+Assumptions!$B$6)/(1-Assumptions!$B$5-Assumptions!$B$7-Assumptions!$B$8-Assumptions!$B$9-Assumptions!$B$10) -> 59.87526 | E6: =ROUNDUP(D6,0)-0.01 -> 59.99 | F6: =E6-B6-C6-(E6*Assumptions!$B$5+Assumptions!$B$6)-E6*Assumptions!$B$7-E6*Assumptions!$B$8-E6*Assumptions!$B$10 -> 12.05319 | G6: =F6/E6 -> 0.20091999
A7: Ceramic Mug 11oz | B7: 6.5 | C7: 4.2 | D7: =(B7+C7+Assumptions!$B$6)/(1-Assumptions!$B$5-Assumptions!$B$7-Assumptions!$B$8-Assumptions!$B$9-Assumptions!$B$10) -> 22.869023 | E7: =ROUNDUP(D7,0)-0.01 -> 22.99 | F7: =E7-B7-C7-(E7*Assumptions!$B$5+Assumptions!$B$6)-E7*Assumptions!$B$7-E7*Assumptions!$B$8-E7*Assumptions!$B$10 -> 4.65619 | G7: =F7/E7 -> 0.2025311
A8: Canvas Tote Bag | B8: 8 | C8: 4.8 | D8: =(B8+C8+Assumptions!$B$6)/(1-Assumptions!$B$5-Assumptions!$B$7-Assumptions!$B$8-Assumptions!$B$9-Assumptions!$B$10) -> 27.234927 | E8: =ROUNDUP(D8,0)-0.01 -> 27.99 | F8: =E8-B8-C8-(E8*Assumptions!$B$5+Assumptions!$B$6)-E8*Assumptions!$B$7-E8*Assumptions!$B$8-E8*Assumptions!$B$10 -> 5.96119 | G8: =F8/E8 -> 0.21297571
A9: Poster Print 18x24 | B9: 7 | C9: 5.5 | D9: =(B9+C9+Assumptions!$B$6)/(1-Assumptions!$B$5-Assumptions!$B$7-Assumptions!$B$8-Assumptions!$B$9-Assumptions!$B$10) -> 26.611227 | E9: =ROUNDUP(D9,0)-0.01 -> 26.99 | F9: =E9-B9-C9-(E9*Assumptions!$B$5+Assumptions!$B$6)-E9*Assumptions!$B$7-E9*Assumptions!$B$8-E9*Assumptions!$B$10 -> 5.58019 | G9: =F9/E9 -> 0.20675028
D10: =IF(AND(B10="",C10=""),"",(B10+C10+Assumptions!$B$6)/(1-Assumptions!$B$5-Assumptions!$B$7-Assumptions!$B$8-Assumptions!$B$9-Assumptions!$B$10)) | E10: =IF(D10="","",ROUNDUP(D10,0)-0.01) | F10: =IF(E10="","",E10-B10-C10-(E10*Assumptions!$B$5+Assumptions!$B$6)-E10*Assumptions!$B$7-E10*Assumptions!$B$8-E10*Assumptions!$B$10) | G10: =IF(F10="","",F10/E10)
D11: =IF(AND(B11="",C11=""),"",(B11+C11+Assumptions!$B$6)/(1-Assumptions!$B$5-Assumptions!$B$7-Assumptions!$B$8-Assumptions!$B$9-Assumptions!$B$10)) | E11: =IF(D11="","",ROUNDUP(D11,0)-0.01) | F11: =IF(E11="","",E11-B11-C11-(E11*Assumptions!$B$5+Assumptions!$B$6)-E11*Assumptions!$B$7-E11*Assumptions!$B$8-E11*Assumptions!$B$10) | G11: =IF(F11="","",F11/E11)
D12: =IF(AND(B12="",C12=""),"",(B12+C12+Assumptions!$B$6)/(1-Assumptions!$B$5-Assumptions!$B$7-Assumptions!$B$8-Assumptions!$B$9-Assumptions!$B$10)) | E12: =IF(D12="","",ROUNDUP(D12,0)-0.01) | F12: =IF(E12="","",E12-B12-C12-(E12*Assumptions!$B$5+Assumptions!$B$6)-E12*Assumptions!$B$7-E12*Assumptions!$B$8-E12*Assumptions!$B$10) | G12: =IF(F12="","",F12/E12)
D13: =IF(AND(B13="",C13=""),"",(B13+C13+Assumptions!$B$6)/(1-Assumptions!$B$5-Assumptions!$B$7-Assumptions!$B$8-Assumptions!$B$9-Assumptions!$B$10)) | E13: =IF(D13="","",ROUNDUP(D13,0)-0.01) | F13: =IF(E13="","",E13-B13-C13-(E13*Assumptions!$B$5+Assumptions!$B$6)-E13*Assumptions!$B$7-E13*Assumptions!$B$8-E13*Assumptions!$B$10) | G13: =IF(F13="","",F13/E13)
D14: =IF(AND(B14="",C14=""),"",(B14+C14+Assumptions!$B$6)/(1-Assumptions!$B$5-Assumptions!$B$7-Assumptions!$B$8-Assumptions!$B$9-Assumptions!$B$10)) | E14: =IF(D14="","",ROUNDUP(D14,0)-0.01) | F14: =IF(E14="","",E14-B14-C14-(E14*Assumptions!$B$5+Assumptions!$B$6)-E14*Assumptions!$B$7-E14*Assumptions!$B$8-E14*Assumptions!$B$10) | G14: =IF(F14="","",F14/E14)
D15: =IF(AND(B15="",C15=""),"",(B15+C15+Assumptions!$B$6)/(1-Assumptions!$B$5-Assumptions!$B$7-Assumptions!$B$8-Assumptions!$B$9-Assumptions!$B$10)) | E15: =IF(D15="","",ROUNDUP(D15,0)-0.01) | F15: =IF(E15="","",E15-B15-C15-(E15*Assumptions!$B$5+Assumptions!$B$6)-E15*Assumptions!$B$7-E15*Assumptions!$B$8-E15*Assumptions!$B$10) | G15: =IF(F15="","",F15/E15)
D16: =IF(AND(B16="",C16=""),"",(B16+C16+Assumptions!$B$6)/(1-Assumptions!$B$5-Assumptions!$B$7-Assumptions!$B$8-Assumptions!$B$9-Assumptions!$B$10)) | E16: =IF(D16="","",ROUNDUP(D16,0)-0.01) | F16: =IF(E16="","",E16-B16-C16-(E16*Assumptions!$B$5+Assumptions!$B$6)-E16*Assumptions!$B$7-E16*Assumptions!$B$8-E16*Assumptions!$B$10) | G16: =IF(F16="","",F16/E16)
D17: =IF(AND(B17="",C17=""),"",(B17+C17+Assumptions!$B$6)/(1-Assumptions!$B$5-Assumptions!$B$7-Assumptions!$B$8-Assumptions!$B$9-Assumptions!$B$10)) | E17: =IF(D17="","",ROUNDUP(D17,0)-0.01) | F17: =IF(E17="","",E17-B17-C17-(E17*Assumptions!$B$5+Assumptions!$B$6)-E17*Assumptions!$B$7-E17*Assumptions!$B$8-E17*Assumptions!$B$10) | G17: =IF(F17="","",F17/E17)
D18: =IF(AND(B18="",C18=""),"",(B18+C18+Assumptions!$B$6)/(1-Assumptions!$B$5-Assumptions!$B$7-Assumptions!$B$8-Assumptions!$B$9-Assumptions!$B$10)) | E18: =IF(D18="","",ROUNDUP(D18,0)-0.01) | F18: =IF(E18="","",E18-B18-C18-(E18*Assumptions!$B$5+Assumptions!$B$6)-E18*Assumptions!$B$7-E18*Assumptions!$B$8-E18*Assumptions!$B$10) | G18: =IF(F18="","",F18/E18)
D19: =IF(AND(B19="",C19=""),"",(B19+C19+Assumptions!$B$6)/(1-Assumptions!$B$5-Assumptions!$B$7-Assumptions!$B$8-Assumptions!$B$9-Assumptions!$B$10)) | E19: =IF(D19="","",ROUNDUP(D19,0)-0.01) | F19: =IF(E19="","",E19-B19-C19-(E19*Assumptions!$B$5+Assumptions!$B$6)-E19*Assumptions!$B$7-E19*Assumptions!$B$8-E19*Assumptions!$B$10) | G19: =IF(F19="","",F19/E19)
A22: Average (filled rows) | E22: =IFERROR(AVERAGE(E5:E20),"") -> 33.59 | F22: =IFERROR(AVERAGE(F5:F20),"") -> 6.87479 | G22: =IFERROR(AVERAGE(G5:G20),"") -> 0.20547029
